[{"model": "blog_app.category", "pk": 1, "fields": {"title": "Спорт"}}, {"model": "blog_app.category", "pk": 2, "fields": {"title": "Музыка"}}, {"model": "blog_app.category", "pk": 3, "fields": {"title": "Политика"}}, {"model": "blog_app.recipe", "pk": 2, "fields": {"title": "Хуляш", "created_at": "2023-03-09T15:04:13.327Z", "views": 669, "category": 1, "publish": true, "description": "Это хуйняяя", "author": 1, "image": ""}}, {"model": "blog_app.recipe", "pk": 3, "fields": {"title": "Крек", "created_at": "2023-03-09T15:11:18.111Z", "views": 100001, "category": 3, "publish": true, "description": "Это очень плохо", "author": 2, "image": "photos/gg.png"}}, {"model": "blog_app.recipe", "pk": 4, "fields": {"title": "Гороховый шута", "created_at": "2023-03-09T15:12:21.820Z", "views": 233, "category": 2, "publish": true, "description": "Симфоническая атака", "author": 1, "image": ""}}, {"model": "blog_app.recipe", "pk": 5, "fields": {"title": "Fanis", "created_at": "2023-03-23T15:29:12.944Z", "views": 1, "category": 3, "publish": true, "description": "Fanis very hard suka bla", "author": 1, "image": "photos/чебурашка.png"}}, {"model": "blog_app.comment", "pk": 1, "fields": {"author": 1, "recipe": 2, "created_at": "2023-03-27T16:01:46.504Z", "content": "fsdfgasdgasdgasdg"}}, {"model": "blog_app.comment", "pk": 3, "fields": {"author": 1, "recipe": 2, "created_at": "2023-04-06T14:44:18.875Z", "content": "asdfasdfasfasfasf\r\n\r\nasfasdasd LOX"}}, {"model": "blog_app.recipecountviews", "pk": 1, "fields": {"session_id": "znnmldnuc26lw992shvdw35d2ruaoif1", "user": null, "recipe": 2}}, {"model": "blog_app.recipecountviews", "pk": 2, "fields": {"session_id": null, "user": 1, "recipe": 4}}, {"model": "blog_app.recipecountviews", "pk": 3, "fields": {"session_id": null, "user": 1, "recipe": 5}}, {"model": "blog_app.recipecountviews", "pk": 4, "fields": {"session_id": null, "user": 1, "recipe": 2}}, {"model": "blog_app.recipecountviews", "pk": 5, "fields": {"session_id": null, "user": 4, "recipe": 2}}, {"model": "blog_app.recipecountviews", "pk": 6, "fields": {"session_id": "cda05rwvukrivp3holhbumznl49c96x8", "user": null, "recipe": 3}}]